<annotation>
	<folder>detect</folder>
	<filename>170889.jpg</filename>
	<path>C:\Users\theoo\OneDrive\Images\TER\detect\170889.jpg</path>
	<source>
		<database>Unknown</database>
	</source>
	<size>
		<width>3175</width>
		<height>4506</height>
		<depth>3</depth>
	</size>
	<segmented>0</segmented>
	<object>
		<name>N35</name>
		<pose>Unspecified</pose>
		<truncated>0</truncated>
		<difficult>0</difficult>
		<bndbox>
			<xmin>970</xmin>
			<ymin>881</ymin>
			<xmax>1570</xmax>
			<ymax>1062</ymax>
		</bndbox>
	</object>
	<object>
		<name>M17</name>
		<pose>Unspecified</pose>
		<truncated>0</truncated>
		<difficult>0</difficult>
		<bndbox>
			<xmin>1528</xmin>
			<ymin>662</ymin>
			<xmax>1732</xmax>
			<ymax>1319</ymax>
		</bndbox>
	</object>
	<object>
		<name>V30</name>
		<pose>Unspecified</pose>
		<truncated>0</truncated>
		<difficult>0</difficult>
		<bndbox>
			<xmin>961</xmin>
			<ymin>1652</ymin>
			<xmax>1713</xmax>
			<ymax>2038</ymax>
		</bndbox>
	</object>
	<object>
		<name>M17</name>
		<pose>Unspecified</pose>
		<truncated>0</truncated>
		<difficult>0</difficult>
		<bndbox>
			<xmin>904</xmin>
			<ymin>2438</ymin>
			<xmax>1132</xmax>
			<ymax>3133</ymax>
		</bndbox>
	</object>
	<object>
		<name>M17</name>
		<pose>Unspecified</pose>
		<truncated>0</truncated>
		<difficult>0</difficult>
		<bndbox>
			<xmin>1118</xmin>
			<ymin>2409</ymin>
			<xmax>1323</xmax>
			<ymax>3133</ymax>
		</bndbox>
	</object>
	<object>
		<name>X8</name>
		<pose>Unspecified</pose>
		<truncated>0</truncated>
		<difficult>0</difficult>
		<bndbox>
			<xmin>1366</xmin>
			<ymin>3185</ymin>
			<xmax>1723</xmax>
			<ymax>3809</ymax>
		</bndbox>
	</object>
</annotation>
