<annotation>
	<folder>detect</folder>
	<filename>69178.jpg</filename>
	<path>C:\Users\theoo\OneDrive\Images\TER\detect\69178.jpg</path>
	<source>
		<database>Unknown</database>
	</source>
	<size>
		<width>3164</width>
		<height>11693</height>
		<depth>3</depth>
	</size>
	<segmented>0</segmented>
	<object>
		<name>V30</name>
		<pose>Unspecified</pose>
		<truncated>0</truncated>
		<difficult>0</difficult>
		<bndbox>
			<xmin>843</xmin>
			<ymin>537</ymin>
			<xmax>1309</xmax>
			<ymax>730</ymax>
		</bndbox>
	</object>
	<object>
		<name>N35</name>
		<pose>Unspecified</pose>
		<truncated>0</truncated>
		<difficult>0</difficult>
		<bndbox>
			<xmin>2228</xmin>
			<ymin>1726</ymin>
			<xmax>2791</xmax>
			<ymax>1889</ymax>
		</bndbox>
	</object>
	<object>
		<name>I10</name>
		<pose>Unspecified</pose>
		<truncated>0</truncated>
		<difficult>0</difficult>
		<bndbox>
			<xmin>1643</xmin>
			<ymin>1345</ymin>
			<xmax>2137</xmax>
			<ymax>1851</ymax>
		</bndbox>
	</object>
	<object>
		<name>M17</name>
		<pose>Unspecified</pose>
		<truncated>0</truncated>
		<difficult>0</difficult>
		<bndbox>
			<xmin>1770</xmin>
			<ymin>1509</ymin>
			<xmax>1955</xmax>
			<ymax>1964</ymax>
		</bndbox>
	</object>
	<object>
		<name>N35</name>
		<pose>Unspecified</pose>
		<truncated>0</truncated>
		<difficult>0</difficult>
		<bndbox>
			<xmin>1597</xmin>
			<ymin>1962</ymin>
			<xmax>2143</xmax>
			<ymax>2097</ymax>
		</bndbox>
	</object>
	<object>
		<name>N35</name>
		<pose>Unspecified</pose>
		<truncated>0</truncated>
		<difficult>0</difficult>
		<bndbox>
			<xmin>2224</xmin>
			<ymin>2237</ymin>
			<xmax>2782</xmax>
			<ymax>2395</ymax>
		</bndbox>
	</object>
	<object>
		<name>N35</name>
		<pose>Unspecified</pose>
		<truncated>0</truncated>
		<difficult>0</difficult>
		<bndbox>
			<xmin>1766</xmin>
			<ymin>2430</ymin>
			<xmax>2132</xmax>
			<ymax>2549</ymax>
		</bndbox>
	</object>
	<object>
		<name>M17</name>
		<pose>Unspecified</pose>
		<truncated>0</truncated>
		<difficult>0</difficult>
		<bndbox>
			<xmin>1620</xmin>
			<ymin>2099</ymin>
			<xmax>1780</xmax>
			<ymax>2545</ymax>
		</bndbox>
	</object>
	<object>
		<name>G43</name>
		<pose>Unspecified</pose>
		<truncated>0</truncated>
		<difficult>0</difficult>
		<bndbox>
			<xmin>1112</xmin>
			<ymin>2268</ymin>
			<xmax>1395</xmax>
			<ymax>2645</ymax>
		</bndbox>
	</object>
	<object>
		<name>N35</name>
		<pose>Unspecified</pose>
		<truncated>0</truncated>
		<difficult>0</difficult>
		<bndbox>
			<xmin>2291</xmin>
			<ymin>3322</ymin>
			<xmax>2709</xmax>
			<ymax>3474</ymax>
		</bndbox>
	</object>
	<object>
		<name>D21</name>
		<pose>Unspecified</pose>
		<truncated>0</truncated>
		<difficult>0</difficult>
		<bndbox>
			<xmin>2293</xmin>
			<ymin>3055</ymin>
			<xmax>2724</xmax>
			<ymax>3224</ymax>
		</bndbox>
	</object>
	<object>
		<name>F35</name>
		<pose>Unspecified</pose>
		<truncated>0</truncated>
		<difficult>0</difficult>
		<bndbox>
			<xmin>1018</xmin>
			<ymin>3182</ymin>
			<xmax>1197</xmax>
			<ymax>3666</ymax>
		</bndbox>
	</object>
	<object>
		<name>V30</name>
		<pose>Unspecified</pose>
		<truncated>0</truncated>
		<difficult>0</difficult>
		<bndbox>
			<xmin>1005</xmin>
			<ymin>3662</ymin>
			<xmax>1537</xmax>
			<ymax>3862</ymax>
		</bndbox>
	</object>
	<object>
		<name>N35</name>
		<pose>Unspecified</pose>
		<truncated>0</truncated>
		<difficult>0</difficult>
		<bndbox>
			<xmin>1618</xmin>
			<ymin>3930</ymin>
			<xmax>2151</xmax>
			<ymax>4070</ymax>
		</bndbox>
	</object>
	<object>
		<name>X8</name>
		<pose>Unspecified</pose>
		<truncated>0</truncated>
		<difficult>0</difficult>
		<bndbox>
			<xmin>2241</xmin>
			<ymin>3584</ymin>
			<xmax>2516</xmax>
			<ymax>4070</ymax>
		</bndbox>
	</object>
	<object>
		<name>M17</name>
		<pose>Unspecified</pose>
		<truncated>0</truncated>
		<difficult>0</difficult>
		<bndbox>
			<xmin>1839</xmin>
			<ymin>4057</ymin>
			<xmax>2007</xmax>
			<ymax>4524</ymax>
		</bndbox>
	</object>
	<object>
		<name>M17</name>
		<pose>Unspecified</pose>
		<truncated>0</truncated>
		<difficult>0</difficult>
		<bndbox>
			<xmin>1997</xmin>
			<ymin>4059</ymin>
			<xmax>2164</xmax>
			<ymax>4516</ymax>
		</bndbox>
	</object>
	<object>
		<name>V30</name>
		<pose>Unspecified</pose>
		<truncated>0</truncated>
		<difficult>0</difficult>
		<bndbox>
			<xmin>1007</xmin>
			<ymin>4484</ymin>
			<xmax>1541</xmax>
			<ymax>4693</ymax>
		</bndbox>
	</object>
	<object>
		<name>D21</name>
		<pose>Unspecified</pose>
		<truncated>0</truncated>
		<difficult>0</difficult>
		<bndbox>
			<xmin>387</xmin>
			<ymin>4057</ymin>
			<xmax>932</xmax>
			<ymax>4214</ymax>
		</bndbox>
	</object>
	<object>
		<name>D21</name>
		<pose>Unspecified</pose>
		<truncated>0</truncated>
		<difficult>0</difficult>
		<bndbox>
			<xmin>395</xmin>
			<ymin>3905</ymin>
			<xmax>941</xmax>
			<ymax>4055</ymax>
		</bndbox>
	</object>
	<object>
		<name>G43</name>
		<pose>Unspecified</pose>
		<truncated>0</truncated>
		<difficult>0</difficult>
		<bndbox>
			<xmin>449</xmin>
			<ymin>4205</ymin>
			<xmax>855</xmax>
			<ymax>4666</ymax>
		</bndbox>
	</object>
	<object>
		<name>V30</name>
		<pose>Unspecified</pose>
		<truncated>0</truncated>
		<difficult>0</difficult>
		<bndbox>
			<xmin>389</xmin>
			<ymin>5080</ymin>
			<xmax>930</xmax>
			<ymax>5280</ymax>
		</bndbox>
	</object>
	<object>
		<name>X8</name>
		<pose>Unspecified</pose>
		<truncated>0</truncated>
		<difficult>0</difficult>
		<bndbox>
			<xmin>557</xmin>
			<ymin>5278</ymin>
			<xmax>747</xmax>
			<ymax>5680</ymax>
		</bndbox>
	</object>
	<object>
		<name>I10</name>
		<pose>Unspecified</pose>
		<truncated>0</truncated>
		<difficult>0</difficult>
		<bndbox>
			<xmin>2234</xmin>
			<ymin>4791</ymin>
			<xmax>2791</xmax>
			<ymax>5291</ymax>
		</bndbox>
	</object>
	<object>
		<name>I10</name>
		<pose>Unspecified</pose>
		<truncated>0</truncated>
		<difficult>0</difficult>
		<bndbox>
			<xmin>1101</xmin>
			<ymin>5649</ymin>
			<xmax>1597</xmax>
			<ymax>6101</ymax>
		</bndbox>
	</object>
	<object>
		<name>F35</name>
		<pose>Unspecified</pose>
		<truncated>0</truncated>
		<difficult>0</difficult>
		<bndbox>
			<xmin>1434</xmin>
			<ymin>5282</ymin>
			<xmax>1578</xmax>
			<ymax>5653</ymax>
		</bndbox>
	</object>
	<object>
		<name>N35</name>
		<pose>Unspecified</pose>
		<truncated>0</truncated>
		<difficult>0</difficult>
		<bndbox>
			<xmin>2278</xmin>
			<ymin>7226</ymin>
			<xmax>2795</xmax>
			<ymax>7393</ymax>
		</bndbox>
	</object>
	<object>
		<name>D4</name>
		<pose>Unspecified</pose>
		<truncated>0</truncated>
		<difficult>0</difficult>
		<bndbox>
			<xmin>1320</xmin>
			<ymin>6895</ymin>
			<xmax>1751</xmax>
			<ymax>7037</ymax>
		</bndbox>
	</object>
	<object>
		<name>X8</name>
		<pose>Unspecified</pose>
		<truncated>0</truncated>
		<difficult>0</difficult>
		<bndbox>
			<xmin>1547</xmin>
			<ymin>7218</ymin>
			<xmax>1768</xmax>
			<ymax>7628</ymax>
		</bndbox>
	</object>
	<object>
		<name>V30</name>
		<pose>Unspecified</pose>
		<truncated>0</truncated>
		<difficult>0</difficult>
		<bndbox>
			<xmin>2297</xmin>
			<ymin>7849</ymin>
			<xmax>2793</xmax>
			<ymax>8032</ymax>
		</bndbox>
	</object>
	<object>
		<name>M17</name>
		<pose>Unspecified</pose>
		<truncated>0</truncated>
		<difficult>0</difficult>
		<bndbox>
			<xmin>995</xmin>
			<ymin>8124</ymin>
			<xmax>1134</xmax>
			<ymax>8543</ymax>
		</bndbox>
	</object>
	<object>
		<name>M17</name>
		<pose>Unspecified</pose>
		<truncated>0</truncated>
		<difficult>0</difficult>
		<bndbox>
			<xmin>1139</xmin>
			<ymin>8122</ymin>
			<xmax>1257</xmax>
			<ymax>8553</ymax>
		</bndbox>
	</object>
	<object>
		<name>V30</name>
		<pose>Unspecified</pose>
		<truncated>0</truncated>
		<difficult>0</difficult>
		<bndbox>
			<xmin>1449</xmin>
			<ymin>8407</ymin>
			<xmax>1689</xmax>
			<ymax>8555</ymax>
		</bndbox>
	</object>
	<object>
		<name>V30</name>
		<pose>Unspecified</pose>
		<truncated>0</truncated>
		<difficult>0</difficult>
		<bndbox>
			<xmin>1687</xmin>
			<ymin>8409</ymin>
			<xmax>1912</xmax>
			<ymax>8549</ymax>
		</bndbox>
	</object>
	<object>
		<name>D4</name>
		<pose>Unspecified</pose>
		<truncated>0</truncated>
		<difficult>0</difficult>
		<bndbox>
			<xmin>1243</xmin>
			<ymin>8643</ymin>
			<xmax>1649</xmax>
			<ymax>8830</ymax>
		</bndbox>
	</object>
	<object>
		<name>D21</name>
		<pose>Unspecified</pose>
		<truncated>0</truncated>
		<difficult>0</difficult>
		<bndbox>
			<xmin>401</xmin>
			<ymin>8641</ymin>
			<xmax>837</xmax>
			<ymax>8803</ymax>
		</bndbox>
	</object>
	<object>
		<name>G17</name>
		<pose>Unspecified</pose>
		<truncated>0</truncated>
		<difficult>0</difficult>
		<bndbox>
			<xmin>2426</xmin>
			<ymin>8637</ymin>
			<xmax>2816</xmax>
			<ymax>9097</ymax>
		</bndbox>
	</object>
</annotation>
